zeroBYT.py
zeroBYT-0.2.dist-info/License.txt
zeroBYT-0.2.dist-info/METADATA
zeroBYT-0.2.dist-info/WHEEL
zeroBYT-0.2.dist-info/top_level.txt
zeroBYT-0.2.dist-info/RECORD
