Metadata-Version: 2.1
Name: zeroBYT
Version: 0.2
Summary: Update : Generates Waveform like Sine, Square, SquareSine
Home-page: https://github.com/aahilashik/zeroBYT
License: UNKNOWN
Platform: UNKNOWN
Classifier: Programming Language :: Python :: 3
Classifier: License :: OSI Approved :: MIT License
Classifier: Operating System :: OS Independent
Requires-Python: >=3.4
